{
  "db_name": "PostgreSQL",
  "query": "SELECT id, user_id, admin_id, email, created_at, expires_at, used_at, token_type FROM token",
  "describe": {
    "columns": [
      {
        "ordinal": 0,
        "name": "id",
        "type_info": "Text"
      },
      {
        "ordinal": 1,
        "name": "user_id",
        "type_info": "Int8"
      },
      {
        "ordinal": 2,
        "name": "admin_id",
        "type_info": "Int8"
      },
      {
        "ordinal": 3,
        "name": "email",
        "type_info": "Text"
      },
      {
        "ordinal": 4,
        "name": "created_at",
        "type_info": "Timestamp"
      },
      {
        "ordinal": 5,
        "name": "expires_at",
        "type_info": "Timestamp"
      },
      {
        "ordinal": 6,
        "name": "used_at",
        "type_info": "Timestamp"
      },
      {
        "ordinal": 7,
        "name": "token_type",
        "type_info": "Text"
      }
    ],
    "parameters": {
      "Left": []
    },
    "nullable": [
      false,
      false,
      true,
      true,
      false,
      false,
      true,
      true
    ]
  },
  "hash": "f6cb6d9cdf5db43582cdb77f3c60335ae28f92e6653abcfd001118a965cb5d36"
}
