{
  "db_name": "PostgreSQL",
  "query": "SELECT device.id, name, wireguard_pubkey, user_id, created, description, device_type \"device_type: DeviceType\" FROM device JOIN \"user\" ON device.user_id = \"user\".id WHERE \"user\".username = $1",
  "describe": {
    "columns": [
      {
        "ordinal": 0,
        "name": "id",
        "type_info": "Int8"
      },
      {
        "ordinal": 1,
        "name": "name",
        "type_info": "Text"
      },
      {
        "ordinal": 2,
        "name": "wireguard_pubkey",
        "type_info": "Text"
      },
      {
        "ordinal": 3,
        "name": "user_id",
        "type_info": "Int8"
      },
      {
        "ordinal": 4,
        "name": "created",
        "type_info": "Timestamp"
      },
      {
        "ordinal": 5,
        "name": "description",
        "type_info": "Text"
      },
      {
        "ordinal": 6,
        "name": "device_type: DeviceType",
        "type_info": {
          "Custom": {
            "name": "device_type",
            "kind": {
              "Enum": [
                "user",
                "network"
              ]
            }
          }
        }
      }
    ],
    "parameters": {
      "Left": [
        "Text"
      ]
    },
    "nullable": [
      false,
      false,
      false,
      false,
      false,
      true,
      false
    ]
  },
  "hash": "f8a52de7a941ae33ce8d04880cfe9d2ddd0c1e7993337e2ca1b16f9519c84a85"
}
