{
  "db_name": "PostgreSQL",
<<<<<<<< HEAD:.sqlx/query-74328fde1221a6fbdd9e924428a293cdb37980c4e24ce6ac77abebd626e8ef83.json
  "query": "SELECT id, \"network_id\",\"url\",\"hostname\",\"connected_at\",\"disconnected_at\",\"has_certificate\",\"certificate_expiry\",\"name\" FROM \"gateway\"",
========
  "query": "SELECT id, \"network_id\",\"url\",\"hostname\",\"connected_at\",\"disconnected_at\",\"has_certificate\",\"certificate_expiry\",\"version\" FROM \"gateway\"",
>>>>>>>> d5d856dc3ec48ae984d1c1a403df9cdaf71face2:.sqlx/query-9655c2e6a8f749fe1ea966dcdc0ea2080a4c27137278b2fb761d3b279b69f9db.json
  "describe": {
    "columns": [
      {
        "ordinal": 0,
        "name": "id",
        "type_info": "Int8"
      },
      {
        "ordinal": 1,
        "name": "network_id",
        "type_info": "Int8"
      },
      {
        "ordinal": 2,
        "name": "url",
        "type_info": "Text"
      },
      {
        "ordinal": 3,
        "name": "hostname",
        "type_info": "Text"
      },
      {
        "ordinal": 4,
        "name": "connected_at",
        "type_info": "Timestamp"
      },
      {
        "ordinal": 5,
        "name": "disconnected_at",
        "type_info": "Timestamp"
      },
      {
        "ordinal": 6,
        "name": "has_certificate",
        "type_info": "Bool"
      },
      {
        "ordinal": 7,
        "name": "certificate_expiry",
        "type_info": "Timestamp"
      },
      {
        "ordinal": 8,
<<<<<<<< HEAD:.sqlx/query-74328fde1221a6fbdd9e924428a293cdb37980c4e24ce6ac77abebd626e8ef83.json
        "name": "name",
========
        "name": "version",
>>>>>>>> d5d856dc3ec48ae984d1c1a403df9cdaf71face2:.sqlx/query-9655c2e6a8f749fe1ea966dcdc0ea2080a4c27137278b2fb761d3b279b69f9db.json
        "type_info": "Text"
      }
    ],
    "parameters": {
      "Left": []
    },
    "nullable": [
      false,
      false,
      false,
      true,
      true,
      true,
      false,
      true,
<<<<<<<< HEAD:.sqlx/query-74328fde1221a6fbdd9e924428a293cdb37980c4e24ce6ac77abebd626e8ef83.json
      false
    ]
  },
  "hash": "74328fde1221a6fbdd9e924428a293cdb37980c4e24ce6ac77abebd626e8ef83"
========
      true
    ]
  },
  "hash": "9655c2e6a8f749fe1ea966dcdc0ea2080a4c27137278b2fb761d3b279b69f9db"
>>>>>>>> d5d856dc3ec48ae984d1c1a403df9cdaf71face2:.sqlx/query-9655c2e6a8f749fe1ea966dcdc0ea2080a4c27137278b2fb761d3b279b69f9db.json
}
