{
  "db_name": "PostgreSQL",
  "query": "SELECT device_id, wireguard_network_id, wireguard_ip as \"wireguard_ip: IpAddr\", preshared_key, is_authorized FROM wireguard_network_device WHERE device_id = $1",
  "describe": {
    "columns": [
      {
        "ordinal": 0,
        "name": "device_id",
        "type_info": "Int8"
      },
      {
        "ordinal": 1,
        "name": "wireguard_network_id",
        "type_info": "Int8"
      },
      {
        "ordinal": 2,
        "name": "wireguard_ip: IpAddr",
        "type_info": "Inet"
      },
      {
        "ordinal": 3,
        "name": "preshared_key",
        "type_info": "Text"
      },
      {
        "ordinal": 4,
        "name": "is_authorized",
        "type_info": "Bool"
      }
    ],
    "parameters": {
      "Left": [
        "Int8"
      ]
    },
    "nullable": [
      false,
      false,
      false,
      true,
      false
    ]
  },
  "hash": "442aac6474b466acc15578483d7d582a6face350a9c4c11db8b32fc251605cd6"
}
