{
  "db_name": "PostgreSQL",
  "query": "SELECT id \"id: _\", name, address, port, pubkey, prvkey, endpoint, dns, allowed_ips, connected_at, mfa_enabled, keepalive_interval, peer_disconnect_threshold FROM wireguard_network WHERE name = $1",
  "describe": {
    "columns": [
      {
        "ordinal": 0,
        "name": "id: _",
        "type_info": "Int8"
      },
      {
        "ordinal": 1,
        "name": "name",
        "type_info": "Text"
      },
      {
        "ordinal": 2,
        "name": "address",
        "type_info": "Inet"
      },
      {
        "ordinal": 3,
        "name": "port",
        "type_info": "Int4"
      },
      {
        "ordinal": 4,
        "name": "pubkey",
        "type_info": "Text"
      },
      {
        "ordinal": 5,
        "name": "prvkey",
        "type_info": "Text"
      },
      {
        "ordinal": 6,
        "name": "endpoint",
        "type_info": "Text"
      },
      {
        "ordinal": 7,
        "name": "dns",
        "type_info": "Text"
      },
      {
        "ordinal": 8,
        "name": "allowed_ips",
        "type_info": "InetArray"
      },
      {
        "ordinal": 9,
        "name": "connected_at",
        "type_info": "Timestamp"
      },
      {
        "ordinal": 10,
        "name": "mfa_enabled",
        "type_info": "Bool"
      },
      {
        "ordinal": 11,
        "name": "keepalive_interval",
        "type_info": "Int4"
      },
      {
        "ordinal": 12,
        "name": "peer_disconnect_threshold",
        "type_info": "Int4"
      }
    ],
    "parameters": {
      "Left": [
        "Text"
      ]
    },
    "nullable": [
      false,
      false,
      false,
      false,
      false,
      false,
      false,
      true,
      false,
      true,
      false,
      false,
      false
    ]
  },
  "hash": "bc6fc6126b695e618619643b8ac92d5fd653c12ec334cd6965fa8b35784275df"
}
